{"pet":{"additional_buffs":[],"buffs":[],"description":{"hidden_abilites":["Quickly moves (dashes) to first target, quickly engages in battle, and casts a barrier that defends against 99% of damage for a short period.","When HP is under 30%, has a 70% chance to dodge enemy attacks. ","Upon first appearing, increases movement and attack speed of all ally units.","Increases movement speed and attack speed of all units by 5%."],"skill1":"Increase basic game speed (0.5%, 1%, 1.5%, 2%, 2.5%)","skill2":" Increase attack power of elf unit in Guild War (3.6%, 7.2%, 10.8%, 14.4%, 18%)","skill3":"Awakens the hidden special ability of [ Senior Wolf Warrior ]"},"from":[46,75,120,381],"img":"img/pets/10.png","pp_per_star":[4]},"petid":"Indy"}
