{
   "1":{
      "unit":"Hippogriff",
      "requirement":5,
      "meta":"Elf"
   },
   "2":{
      "unit":"Dark Priestess",
      "requirement":2,
      "meta":"Elf"
   },
   "3":{
      "unit":"Priest",
      "requirement":3,
      "meta":"Elf"
   },
   "4":{
      "unit":"Dark Archer",
      "requirement":12,
      "meta":"Elf"
   },
   "5":{
      "unit":"Fairy",
      "requirement":13,
      "meta":" Elf"
   },
   "6":{
      "unit":"Priest",
      "requirement":8,
      "meta":"Elf"
   },
   "7":{
      "unit":"Hippogriff",
      "requirement":10,
      "meta":"Elf"
   },
   "8":{
      "unit":"Shadow Knight",
      "requirement":12,
      "meta":"Elf"
   },
   "9":{
      "unit":"Hippogriff",
      "requirement":20,
      "meta":"Undead"
   },
   "10":{
      "unit":"Dark Archer",
      "requirement":20,
      "meta":"Orc"
   },
   "11":{
      "unit":"Frost Demon",
      "requirement":12,
      "meta":"Orc"
   },
   "12":{
      "unit":"War Bear Rider",
      "requirement":12,
      "meta":"Orc"
   },
   "13":{
      "unit":"Sorcerer",
      "requirement":15,
      "meta":"Orc"
   },
   "14":{
      "unit":"Battle Hornist",
      "requirement":10,
      "meta":"Orc"
   },
   "15":{
      "unit":"Naga Knight",
      "requirement":10,
      "meta":"Orc"
   },
   "16":{
      "unit":"Frost Demon",
      "requirement":20,
      "meta":"Orc"
   },
   "17":{
      "unit":"War Bear Rider",
      "requirement":20,
      "meta":"Orc"
   },
   "18":{
      "unit":"Winged Knight",
      "requirement":20,
      "meta":"Orc"
   },
   "19":{
      "unit":"Dark Elf",
      "requirement":6,
      "meta":"Undead"
   },
   "20":{
      "unit":"Royal Druid",
      "requirement":25,
      "meta":"Undead"
   },
   "21":{
      "unit":"Astral Captain",
      "requirement":10,
      "meta":"Undead"
   },
   "22":{
      "unit":"Crow Knight",
      "requirement":15,
      "meta":"Undead"
   },
   "23":{
      "unit":"Musketress",
      "requirement":15,
      "meta":"Undead"
   },
   "24":{
      "unit":"Astral Captain",
      "requirement":15,
      "meta":"Undead"
   }
}